lambda_utils/__init__.py
lambda_utils/request.py
lambda_utils/response.py
codeca_lambda_utils-1.0.2.dist-info/METADATA
codeca_lambda_utils-1.0.2.dist-info/WHEEL
codeca_lambda_utils-1.0.2.dist-info/top_level.txt
codeca_lambda_utils-1.0.2.dist-info/RECORD
